pyrebase/__init__.py
pyrebase/pyrebase.py
sseclient/__init__.py
sseclient/sseclient.py
tyrebase-1.0.30.dist-info/METADATA
tyrebase-1.0.30.dist-info/WHEEL
tyrebase-1.0.30.dist-info/top_level.txt
tyrebase-1.0.30.dist-info/RECORD
