Metadata-Version: 2.1
Name: tyrebase
Version: 1.0.30
Summary: A simple python wrapper for the Firebase API forked from https://github.com/thisbejim/Pyrebase
Home-page: https://github.com/tupio/Pyrebase/
Author: James Childs-Maidment, Denil Verghese
Author-email: UNKNOWN
License: MIT
Keywords: Firebase Wrapper
Platform: UNKNOWN
Classifier: Development Status :: 3 - Alpha
Classifier: Intended Audience :: Developers
Classifier: License :: OSI Approved :: MIT License
Classifier: Programming Language :: Python :: 3.7
Requires-Dist: requests (==2.11.1)
Requires-Dist: gcloud (==0.18.3)
Requires-Dist: oauth2client (==3.0.0)
Requires-Dist: requests-toolbelt (==0.9.1)
Requires-Dist: python-jwt (==2.0.1)
Requires-Dist: pycryptodome (==3.9.6)
